MMBP/__init__.py
MMBP/core.py
MMBP/likeJS.py
MMBP-1.4.1.0.2.dist-info/LICENSE
MMBP-1.4.1.0.2.dist-info/METADATA
MMBP-1.4.1.0.2.dist-info/WHEEL
MMBP-1.4.1.0.2.dist-info/top_level.txt
MMBP-1.4.1.0.2.dist-info/RECORD
